core/__init__.py
core/config_manager.py
core/device_manager.py
core/exit_codes.py
core/framework_launcher.py
core/report_generator.py
core/test_case.py
core/test_report_json_guide.md
core/test_runner.py
core/utils/__init__.py
core/utils/file_utils.py
core/utils/stability_ci.py
core/utils/traversal_ci.py
core/utils/traversal_util.py
utest_auto_core-0.1.26.dist-info/METADATA
utest_auto_core-0.1.26.dist-info/WHEEL
utest_auto_core-0.1.26.dist-info/RECORD
