Metadata-Version: 2.4
Name: utest-auto-core
Version: 0.1.26
Summary: UTest 自动化测试框架核心包（core 模块）
Author-email: lain <lainxxu@tencent.com>
Keywords: android,automation,ios,performance,testing,ubox
Classifier: Programming Language :: Python :: 3
Requires-Python: >=3.9.5
Requires-Dist: androguard==3.3.5
Requires-Dist: numpy~=1.23.0
Requires-Dist: openpyxl>=3.1.2
Requires-Dist: pillow>=10.0.0
Requires-Dist: pyyaml>=6.0
Requires-Dist: ubox-py-sdk>=0.1.42
